README.md
setup.cfg
setup.py
torchphm/__init__.py
torchphm/beta_hpss.py
torchphm/functional.py
torchphm/layers.py
torchphm.egg-info/PKG-INFO
torchphm.egg-info/SOURCES.txt
torchphm.egg-info/dependency_links.txt
torchphm.egg-info/requires.txt
torchphm.egg-info/top_level.txt