Metadata-Version: 2.1
Name: torchphm
Version: 1.1.7
Summary: pick feature for phm
Home-page: https://gitee.com/ultrapower_cd_2364839934_admin/phm_feature_torch
Author: police
Author-email: criminal@qq.com
License: MIT
Platform: UNKNOWN
Classifier: Programming Language :: Python :: 3
Classifier: License :: OSI Approved :: MIT License
Classifier: Operating System :: OS Independent
Provides-Extra: tests
